polymarket_telegram/__init__.py
polymarket_telegram/config.py
polymarket_telegram/processor.py
polymarket_telegram/scheduler.py
polymarket_telegram/sender.py
polymarket_telegram-0.1.0.dist-info/METADATA
polymarket_telegram-0.1.0.dist-info/WHEEL
polymarket_telegram-0.1.0.dist-info/RECORD
