Metadata-Version: 2.4
Name: polymarket-telegram
Version: 0.1.0
Summary: Telegram notification sender for Polymarket market data
Requires-Python: >=3.10
Requires-Dist: apscheduler>=3.10.0
Requires-Dist: httpx>=0.27.0
Requires-Dist: polymarket-fetcher
Requires-Dist: pydantic>=2.0
Requires-Dist: python-dotenv>=1.0.0
Requires-Dist: pyyaml>=6.0
Provides-Extra: all
Requires-Dist: httpx-socks>=0.9.0; extra == 'all'
Requires-Dist: httpx>=0.27.0; extra == 'all'
Requires-Dist: pytest-asyncio>=0.21.0; extra == 'all'
Requires-Dist: pytest-cov>=4.0.0; extra == 'all'
Requires-Dist: pytest-mock>=3.10.0; extra == 'all'
Requires-Dist: pytest>=7.0.0; extra == 'all'
Provides-Extra: dev
Requires-Dist: httpx>=0.27.0; extra == 'dev'
Requires-Dist: pytest-asyncio>=0.21.0; extra == 'dev'
Requires-Dist: pytest-cov>=4.0.0; extra == 'dev'
Requires-Dist: pytest-mock>=3.10.0; extra == 'dev'
Requires-Dist: pytest>=7.0.0; extra == 'dev'
Provides-Extra: socks
Requires-Dist: httpx-socks>=0.9.0; extra == 'socks'
